yosai_alchemystore/__init__.py
yosai_alchemystore/accountstore/__init__.py
yosai_alchemystore/accountstore/accountstore.py
yosai_alchemystore/conf/__init__.py
yosai_alchemystore/conf/create_populate_db.py
yosai_alchemystore/conf/settings.py
yosai_alchemystore/meta/__init__.py
yosai_alchemystore/meta/meta.py
yosai_alchemystore/models/__init__.py
yosai_alchemystore/models/models.py
yosai_alchemystore-0.3.0.post1.dist-info/DESCRIPTION.rst
yosai_alchemystore-0.3.0.post1.dist-info/METADATA
yosai_alchemystore-0.3.0.post1.dist-info/RECORD
yosai_alchemystore-0.3.0.post1.dist-info/WHEEL
yosai_alchemystore-0.3.0.post1.dist-info/metadata.json
yosai_alchemystore-0.3.0.post1.dist-info/top_level.txt
