Metadata-Version: 2.0
Name: yosai-alchemystore
Version: 0.3.0.post1
Summary: An RDBMS solution for Yosai, featuring a flat RBAC data model
Home-page: http://www.github.com/yosaiproject/yosai_alchemystore
Author: Darin Gordon
Author-email: dkcdkg@gmail.com
License: Apache License 2.0
Keywords: sqlalchemy rbac yosai
Platform: UNKNOWN
Classifier: Development Status :: 4 - Beta
Classifier: Intended Audience :: Developers
Classifier: License :: OSI Approved :: Apache Software License
Classifier: Programming Language :: Python
Classifier: Programming Language :: Python :: 3
Classifier: Programming Language :: Python :: 3.4
Classifier: Programming Language :: Python :: 3.5
Classifier: Topic :: Security
Classifier: Topic :: Software Development :: Libraries :: Application Frameworks
Classifier: Topic :: Software Development :: Libraries :: Python Modules
Requires-Dist: yosai
Requires-Dist: sqlalchemy
Requires-Dist: psycopg2
